[
  {"number": 1, "ar": "الرحمن", "en": "Ar-Rahman", "meaning": "الرحمن الذي رحمته عامة على جميع الخلق"},
  {"number": 2, "ar": "الرحيم", "en": "Ar-Raheem", "meaning": "الرحيم بالمؤمنين خاصة"},
  {"number": 3, "ar": "الملك", "en": "Al-Malik", "meaning": "المليك الذي له الأمر والنهي"},
  {"number": 4, "ar": "القدوس", "en": "Al-Quddus", "meaning": "الطاهر من العيوب والنقائص"},
  {"number": 5, "ar": "السلام", "en": "As-Salam", "meaning": "الذي سلم من كل عيب ونجا من كل نقص"},
  {"number": 6, "ar": "المؤمن", "en": "Al-Mu'min", "meaning": "الذي أمن خلقه من ظلمه"},
  {"number": 7, "ar": "المهيمن", "en": "Al-Muhaymin", "meaning": "الذي هو شهيد على أفعال خلقه"},
  {"number": 8, "ar": "العزيز", "en": "Al-Aziz", "meaning": "الذي لا يغلب ولا يُمانع"},
  {"number": 9, "ar": "الجبار", "en": "Al-Jabbar", "meaning": "الذي يجبر الكسر ويعين الضعيف"},
  {"number": 10, "ar": "المتكبر", "en": "Al-Mutakabbir", "meaning": "الذي يتعالى عن صفات الخلق"},
  {"number": 11, "ar": "الخالق", "en": "Al-Khaliq", "meaning": "الذي يقدر على إيجاد الأشياء"},
  {"number": 12, "ar": "البارئ", "en": "Al-Bari", "meaning": "الذي خلق الخلق عن تكوين لا مثال"},
  {"number": 13, "ar": "المصور", "en": "Al-Musawwir", "meaning": "الذي صوّر خلقه كيف شاء"},
  {"number": 14, "ar": "الغفار", "en": "Al-Ghaffar", "meaning": "الذي يكثر الستر والغفران"},
  {"number": 15, "ar": "القهار", "en": "Al-Qahhar", "meaning": "الذي يقهر خلقه بسلطانه"},
  {"number": 16, "ar": "الوهاب", "en": "Al-Wahhab", "meaning": "الذي يهب العطاء بلا عوض"},
  {"number": 17, "ar": "الرزاق", "en": "Ar-Razzaq", "meaning": "الذي يرزق جميع الخلق"},
  {"number": 18, "ar": "الفتاح", "en": "Al-Fattah", "meaning": "الذي يفتح المغلقات"},
  {"number": 19, "ar": "العليم", "en": "Al-Aleem", "meaning": "الذي لا يخفى عليه شيء"},
  {"number": 20, "ar": "القابض", "en": "Al-Qabid", "meaning": "الذي يقبض الرزق عمن يشاء"},
  {"number": 21, "ar": "الباسط", "en": "Al-Basit", "meaning": "الذي يبسط الرزق لمن يشاء"},
  {"number": 22, "ar": "الخافض", "en": "Al-Khafid", "meaning": "الذي يخفض الأقوياء"},
  {"number": 23, "ar": "الرافع", "en": "Ar-Rafi", "meaning": "الذي يرفع الضعفاء"},
  {"number": 24, "ar": "المعز", "en": "Al-Mu'izz", "meaning": "الذي يعز من يشاء"},
  {"number": 25, "ar": "المذل", "en": "Al-Mudhill", "meaning": "الذي يذل من يشاء"},
  {"number": 26, "ar": "السميع", "en": "As-Samee", "meaning": "الذي يسمع كل شيء"},
  {"number": 27, "ar": "البصير", "en": "Al-Baseer", "meaning": "الذي يرى كل شيء"},
  {"number": 28, "ar": "الحكم", "en": "Al-Hakam", "meaning": "الحاكم الذي لا يُرد حكمه"},
  {"number": 29, "ar": "العدل", "en": "Al-Adl", "meaning": "العادل في حكمه"},
  {"number": 30, "ar": "اللطيف", "en": "Al-Lateef", "meaning": "الذي يعلم دقائق الأمور"},
  {"number": 31, "ar": "الخبير", "en": "Al-Khabeer", "meaning": "الذي لا يخفى عليه خافية"},
  {"number": 32, "ar": "الحليم", "en": "Al-Haleem", "meaning": "الذي لا يعاجل بالعقوبة"},
  {"number": 33, "ar": "العظيم", "en": "Al-Azeem", "meaning": "الذي لا عظمة إلا وهو أعظم"},
  {"number": 34, "ar": "الغفور", "en": "Al-Ghafoor", "meaning": "الذي يكثر الغفران"},
  {"number": 35, "ar": "الشكور", "en": "Ash-Shakoor", "meaning": "الذي يجزي بالقليل الكثير"},
  {"number": 36, "ar": "العلي", "en": "Al-Aliyy", "meaning": "الذي لا شيء أعلى منه"},
  {"number": 37, "ar": "الكبير", "en": "Al-Kabeer", "meaning": "الذي لا شيء أكبر منه"},
  {"number": 38, "ar": "الحفيظ", "en": "Al-Hafeez", "meaning": "الذي يحفظ خلقه"},
  {"number": 39, "ar": "المقيت", "en": "Al-Muqeet", "meaning": "الذي يوصل أقوات خلقه"},
  {"number": 40, "ar": "الحسيب", "en": "Al-Haseeb", "meaning": "الكافي الذي يتوكل عليه"},
  {"number": 41, "ar": "الجليل", "en": "Al-Jaleel", "meaning": "الذي له الجلال والعظمة"},
  {"number": 42, "ar": "الكريم", "en": "Al-Kareem", "meaning": "الذي يكثر الخير والإحسان"},
  {"number": 43, "ar": "الرقيب", "en": "Ar-Raqeeb", "meaning": "الذي يراقب خلقه"},
  {"number": 44, "ar": "المجيب", "en": "Al-Mujeeb", "meaning": "الذي يجيب دعاء الداعين"},
  {"number": 45, "ar": "الواسع", "en": "Al-Waasi", "meaning": "الذي وسع رحمته كل شيء"},
  {"number": 46, "ar": "الحكيم", "en": "Al-Hakeem", "meaning": "الذي يضع الأشياء في مواضعها"},
  {"number": 47, "ar": "الودود", "en": "Al-Wadood", "meaning": "الذي يحب عباده المؤمنين"},
  {"number": 48, "ar": "المجيد", "en": "Al-Majeed", "meaning": "الذي وسع كرمه وبره"},
  {"number": 49, "ar": "الباعث", "en": "Al-Ba'ith", "meaning": "الذي يبعث الخلائق يوم القيامة"},
  {"number": 50, "ar": "الشهيد", "en": "Ash-Shaheed", "meaning": "الذي لا يغيب عنه شيء"},
  {"number": 51, "ar": "الحق", "en": "Al-Haqq", "meaning": "الذي هو الحق المبين"},
  {"number": 52, "ar": "الوكيل", "en": "Al-Wakeel", "meaning": "الذي يتولى أمور خلقه"},
  {"number": 53, "ar": "القوي", "en": "Al-Qawiyy", "meaning": "الذي لا تزل قوته"},
  {"number": 54, "ar": "المتين", "en": "Al-Mateen", "meaning": "الذي لا يُهزم ولا يُغلب"},
  {"number": 55, "ar": "الولي", "en": "Al-Waliyy", "meaning": "الذي يتولى المؤمنين"},
  {"number": 56, "ar": "الحميد", "en": "Al-Hameed", "meaning": "الذي يستحق الحمد والثناء"},
  {"number": 57, "ar": "المحصي", "en": "Al-Muhsi", "meaning": "الذي يحصي كل شيء"},
  {"number": 58, "ar": "المبدئ", "en": "Al-Mubdi", "meaning": "الذي بدأ الخلق"},
  {"number": 59, "ar": "المعيد", "en": "Al-Mu'eed", "meaning": "الذي يعيد الخلق بعد الموت"},
  {"number": 60, "ar": "المحيي", "en": "Al-Muhyi", "meaning": "الذي يحيي الخلق"},
  {"number": 61, "ar": "المميت", "en": "Al-Mumeet", "meaning": "الذي يميت الخلق"},
  {"number": 62, "ar": "الحي", "en": "Al-Hayy", "meaning": "الذي لا يموت"},
  {"number": 63, "ar": "القيوم", "en": "Al-Qayyum", "meaning": "الذي يقوم بنفسه ويقوم به كل شيء"},
  {"number": 64, "ar": "الواجد", "en": "Al-Waajid", "meaning": "الذي لا يعوزه شيء"},
  {"number": 65, "ar": "الماجد", "en": "Al-Maajid", "meaning": "الذي وسع كرمه وبره"},
  {"number": 66, "ar": "الواحد", "en": "Al-Waahid", "meaning": "الواحد الذي لا شريك له"},
  {"number": 67, "ar": "الصمد", "en": "As-Samad", "meaning": "الذي يُقصد في الحوائج"},
  {"number": 68, "ar": "القادر", "en": "Al-Qaadir", "meaning": "الذي يقدر على كل شيء"},
  {"number": 69, "ar": "المقتدر", "en": "Al-Muqtadir", "meaning": "الذي ينفذ ما يشاء بقوته"},
  {"number": 70, "ar": "المقدم", "en": "Al-Muqaddim", "meaning": "الذي يقدم من يشاء"},
  {"number": 71, "ar": "المؤخر", "en": "Al-Mu'akhkhir", "meaning": "الذي يؤخر من يشاء"},
  {"number": 72, "ar": "الأول", "en": "Al-Awwal", "meaning": "الذي ليس قبله شيء"},
  {"number": 73, "ar": "الآخر", "en": "Al-Aakhir", "meaning": "الذي ليس بعده شيء"},
  {"number": 74, "ar": "الظاهر", "en": "Az-Zaahir", "meaning": "الذي لا شيء فوقه"},
  {"number": 75, "ar": "الباطن", "en": "Al-Baatin", "meaning": "الذي لا شيء دونه"},
  {"number": 76, "ar": "الوالي", "en": "Al-Waali", "meaning": "المتصرف في الخلائق"},
  {"number": 77, "ar": "المتعالي", "en": "Al-Muta'aali", "meaning": "الذي يتعالى عن وصف الخلق"},
  {"number": 78, "ar": "البر", "en": "Al-Barr", "meaning": "الذي يكثر إحسانه وبره"},
  {"number": 79, "ar": "التواب", "en": "At-Tawwab", "meaning": "الذي يتوب على عباده"},
  {"number": 80, "ar": "المنتقم", "en": "Al-Muntaqim", "meaning": "الذي ينتصر من أعدائه"},
  {"number": 81, "ar": "العفو", "en": "Al-Afuww", "meaning": "الذي يمحو السيئات"},
  {"number": 82, "ar": "الرؤوف", "en": "Ar-Ra'oof", "meaning": "الذي يرحم عباده"},
  {"number": 83, "ar": "مالك الملك", "en": "Maalik-ul-Mulk", "meaning": "الذي يتصرف في ملكه كيف يشاء"},
  {"number": 84, "ar": "ذو الجلال والإكرام", "en": "Dhu-l-Jalaali wa-l-Ikram", "meaning": "الذي له الجلال والإكرام"},
  {"number": 85, "ar": "المقسط", "en": "Al-Muqsit", "meaning": "الذي يعدل في حكمه"},
  {"number": 86, "ar": "الجامع", "en": "Al-Jaami", "meaning": "الذي يجمع الخلائق يوم القيامة"},
  {"number": 87, "ar": "الغني", "en": "Al-Ghaniyy", "meaning": "الذي لا يحتاج إلى شيء"},
  {"number": 88, "ar": "المغني", "en": "Al-Mughni", "meaning": "الذي يغني من يشاء"},
  {"number": 89, "ar": "المانع", "en": "Al-Maani", "meaning": "الذي يمنع ما يشاء"},
  {"number": 90, "ar": "الضار", "en": "Ad-Daarr", "meaning": "الذي يضر من يشاء"},
  {"number": 91, "ar": "النافع", "en": "An-Naafi", "meaning": "الذي ينفع من يشاء"},
  {"number": 92, "ar": "النور", "en": "An-Noor", "meaning": "الذي يرشد الخلق إلى الحق"},
  {"number": 93, "ar": "الهادي", "en": "Al-Haadi", "meaning": "الذي يهدي من يشاء"},
  {"number": 94, "ar": "البديع", "en": "Al-Badi", "meaning": "الذي خلق الخلق بلا مثال"},
  {"number": 95, "ar": "الباقي", "en": "Al-Baaqi", "meaning": "الذي لا يفنى"},
  {"number": 96, "ar": "الوارث", "en": "Al-Waarith", "meaning": "الذي يرث الخلائق"},
  {"number": 97, "ar": "الرشيد", "en": "Ar-Rasheed", "meaning": "الذي يرشد الخلق إلى مصالحهم"},
  {"number": 98, "ar": "الصبور", "en": "As-Saboor", "meaning": "الذي لا يعاجل بالعقوبة"},
  {"number": 99, "ar": "الله", "en": "Allah", "meaning": "الاسم الأعظم الذي لا يسمى به غيره"}
]
